PyDrawille/__init__.py
PyDrawille/main.py
pydrawille-0.0.1.2.dist-info/METADATA
pydrawille-0.0.1.2.dist-info/WHEEL
pydrawille-0.0.1.2.dist-info/entry_points.txt
pydrawille-0.0.1.2.dist-info/licenses/LICENSE
pydrawille-0.0.1.2.dist-info/RECORD
