Metadata-Version: 2.4
Name: PyDrawille
Version: 0.0.1.2
Summary: Using Unicode braille characters to draw pixels in console.
Keywords: console,drawille,unicode,braille,pixel,ascii,image
Author-Email: =?utf-8?b?6YeR576/RWlsbGVz?= <EillesWan@outlook.com>
License-Expression: Apache-2.0
Classifier: Environment :: Console
Classifier: Intended Audience :: Developers
Classifier: Operating System :: OS Independent
Classifier: Topic :: Software Development :: Libraries
Classifier: Programming Language :: Python
Classifier: Programming Language :: Python :: 3
Project-URL: Homepage, https://github.com/EillesWan/PyDrawille
Project-URL: Issues, https://github.com/EillesWan/PyDrawille/issues
Requires-Python: >=3.8
Requires-Dist: numpy
Requires-Dist: pillow>=10.0.0
Provides-Extra: dev
Requires-Dist: twine; extra == "dev"
